my_task_library/__init__.py
my_task_library/flyte_entities.py
my_task_library/py.typed
my_task_library-0.4.0.dist-info/WHEEL
my_task_library-0.4.0.dist-info/METADATA
my_task_library-0.4.0.dist-info/RECORD
