Metadata-Version: 2.3
Name: my-task-library
Version: 0.4.0
Summary: Add your description here
Author: Yee Hing Tong
Author-email: Yee Hing Tong <wild-endeavor@users.noreply.github.com>
Requires-Dist: flyte>=2.0.0b25
Requires-Python: >=3.10
